microsoft_agents_a365/observability/extensions/langchain/__init__.py
microsoft_agents_a365/observability/extensions/langchain/tracer.py
microsoft_agents_a365/observability/extensions/langchain/tracer_instrumentor.py
microsoft_agents_a365/observability/extensions/langchain/utils.py
microsoft_agents_a365_observability_extensions_langchain-0.2.1.dev9.dist-info/METADATA
microsoft_agents_a365_observability_extensions_langchain-0.2.1.dev9.dist-info/WHEEL
microsoft_agents_a365_observability_extensions_langchain-0.2.1.dev9.dist-info/top_level.txt
microsoft_agents_a365_observability_extensions_langchain-0.2.1.dev9.dist-info/RECORD
